espy_contact/__init__.py
espy_contact/model/__init__.py
espy_contact/model/messaging.py
espy_contact/model/models.py
espy_contact/model/reach.py
espy_contact/model/tranx.py
espy_contact/schema/__init__.py
espy_contact/schema/blog.py
espy_contact/schema/campus.py
espy_contact/schema/messaging.py
espy_contact/schema/mgcampus.py
espy_contact/schema/reach.py
espy_contact/schema/schema.py
espy_contact/schema/tranx.py
espy_contact/service/__init__.py
espy_contact/service/service.py
espy_contact/util/CONSTANTS.py
espy_contact/util/__init__.py
espy_contact/util/config.py
espy_contact/util/db.py
espy_contact/util/enums.py
espy_contact/util/esread.py
espy_contact/util/pg.py
tests/__init__.py
tests/test_copyright.py
tests/test_validators.py
espy_contact-2.2.7.dist-info/LICENSE
espy_contact-2.2.7.dist-info/METADATA
espy_contact-2.2.7.dist-info/WHEEL
espy_contact-2.2.7.dist-info/top_level.txt
espy_contact-2.2.7.dist-info/RECORD
