Metadata-Version: 2.1
Name: espy-contact
Version: 2.2.7
Summary: ESSL users management
Home-page: UNKNOWN
Author: Femi Adigun
Author-email: femi.adigun@myeverlasting.net
License: MIT
Keywords: fastapi,ESSL,ReachAI,Horace
Platform: UNKNOWN
License-File: LICENSE
Requires-Dist: bcrypt >=4.2.1
Requires-Dist: pytest >=8.1.1
Requires-Dist: pydantic >=2.10.6
Requires-Dist: sqlalchemy >=2.0.37
Requires-Dist: PyYAML >=6.0.1
